cfg2qr/__init__.py
cfg2qr/file_manip.py
cfg2qr/main.py
cfg2qr/qr_transformations.py
cfg2qr-0.1.8.dist-info/METADATA
cfg2qr-0.1.8.dist-info/WHEEL
cfg2qr-0.1.8.dist-info/entry_points.txt
cfg2qr-0.1.8.dist-info/top_level.txt
cfg2qr-0.1.8.dist-info/RECORD
