Metadata-Version: 2.1
Name: cfg2qr
Version: 0.1.8
Summary: Small personal project to learn about Python packaging.
Home-page: https://github.com/kristin54/qr-code
Author: Kristina
License: MIT
Keywords: qr-code project
Platform: UNKNOWN
Classifier: License :: OSI Approved :: MIT License
Classifier: Programming Language :: Python :: 3.7
Classifier: Programming Language :: Python :: 3.8
Classifier: Programming Language :: Python :: 3.9
Classifier: Programming Language :: Python :: 3 :: Only
Requires-Dist: opencv-python (==4.5.5.62)
Requires-Dist: pyYAML (==6.0)
Requires-Dist: qrcode[pil]
